{
  "Buenavista": {
    "1": "Cabaña",
    "2": "Costa Ana",
    "3": "El Cruce",
    "4": "Guayabito",
    "5": "Mónico",
    "6": "Samén Abajo",
    "7": "San José",
    "8": "Thiales",
    "9": "Valle del Río"
  },
  "Cote": {
    "1": "Altagracia",
    "2": "Alto Sahíno",
    "3": "Bajo Cartagos",
    "4": "Pato",
    "5": "Pejibaye",
    "6": "Pimiento",
    "7": "Quebradón"
  },
  "Katira": {
    "1": "Cabaña",
    "2": "Colonia Naranjeña",
    "3": "El Valle",
    "4": "Florida",
    "5": "Las Letras",
    "6": "La Paz",
    "7": "La Unión",
    "8": "Llano Bonito 1",
    "9": "Llano Bonito 2",
    "10": "Palmera",
    "11": "Río Celeste",
    "12": "Tujankir 1",
    "13": "Tujankir 2"
  },
  "San Rafael": {
    "1": "San Rafael",
    "2": "Betania",
    "3": "Buenos Aires",
    "4": "Curirre",
    "5": "El Edén",
    "6": "El Silencio",
    "7": "El Sol",
    "8": "Flor",
    "9": "Garita",
    "10": "Guayabo",
    "11": "Jade",
    "12": "La Granja",
    "13": "La Rivera",
    "14": "Los Ángeles",
    "15": "Maquencal",
    "16": "Margarita",
    "17": "Montealegre",
    "18": "Moravia",
    "19": "Verde",
    "20": "Muerte",
    "21": "Palmera",
    "22": "Pataste",
    "23": "Pataste Abajo",
    "24": "Poma",
    "25": "Puerto Nuevo",
    "26": "Samén Arriba",
    "27": "San Juan",
    "28": "San Luis",
    "29": "San Miguel",
    "30": "Santa Fé",
    "31": "Santa Marta",
    "32": "Tonjibe",
    "33": "Treminio",
    "34": "Triunfo",
    "35": "Viento Fresco"
  }
}
